esprepomanager/__init__.py
esprepomanager/__main__.py
esprepomanager/config.py
esprepomanager/person.py
esprepomanager/repo.py
esprepomanager/team.py
esprepomanager/utils.py
esprepomanager/gitlab/__init__.py
esprepomanager/gitlab/group.py
esprepomanager/gitlab/project.py
esprepomanager/gitlab/user.py
esprepomanager-1.5.7.dist-info/LICENSE
esprepomanager-1.5.7.dist-info/METADATA
esprepomanager-1.5.7.dist-info/WHEEL
esprepomanager-1.5.7.dist-info/entry_points.txt
esprepomanager-1.5.7.dist-info/top_level.txt
esprepomanager-1.5.7.dist-info/RECORD
